{"mean":{"confidence_interval":{"confidence_level":0.95,"lower_bound":5297.304887925523,"upper_bound":5387.421025477483},"point_estimate":5340.430382188888,"standard_error":22.957342237917693},"median":{"confidence_interval":{"confidence_level":0.95,"lower_bound":5228.2722513089,"upper_bound":5281.8480948225715},"point_estimate":5253.19188022412,"standard_error":15.011934397314013},"median_abs_dev":{"confidence_interval":{"confidence_level":0.95,"lower_bound":77.65637488290348,"upper_bound":197.24758749191201},"point_estimate":124.9947238695224,"standard_error":30.383589358855623},"slope":{"confidence_interval":{"confidence_level":0.95,"lower_bound":5401.714835217243,"upper_bound":5536.230075968966},"point_estimate":5467.509425553792,"standard_error":34.31523730853311},"std_dev":{"confidence_interval":{"confidence_level":0.95,"lower_bound":172.34683250298252,"upper_bound":292.49709158024547},"point_estimate":230.7403354055445,"standard_error":31.417765554920653}}